{
  "含义": "指离开、前往、消除等意义",
  "字形": "去字由"土"和"厂"两个部件组成,表示离开和行进的动作",
  "读音": "qù",
  "字源": "从土,厂声。本义指离开或前往,后引申为除去、消失等含义。",
  "常用词组": [
    "去年",
    "去世",
    "去哪儿",
    "去休息",
    "去买东西",
    "去上班"
  ],
  "成语": [
    "去留两难",
    "去其糟粕",
    "去芜存菁",
    "莫去莫来",
    "拔去蒂叶"
  ],
  "例句": [
    "我明天就要去北京出差了。",
    "老奶奶已经去世一年了,我们很怀念她。",
    "你下班后去哪儿呢?要不要一起去吃饭?",
    "我们要去掉这些无用的信息,只保留有价值的内容。",
    "这位同事总是来来去去,我们很难与他沟通。"
  ],
  "短故事": [
    "有一位年轻人充满理想,决心去到更远的地方追求自己的事业梦想。经历了重重困难和挫折后,他终于实现了心中的理想,成为一名成功的企业家。这个故事告诉我们,只要有坚定的决心,再艰难的路也能去到终点。",
    "从前有一位出家人,他修行多年,最终决定去世界各地弘扬佛法。他走遍大江南北,去除人们内心的烦恼,使很多人获得了精神上的慰藉。临终前,他说:我虽然要去另一个世界,但我的精神将永远留在这里,继续指引众生。"
  ],
  "诗词": [
    "春望 - 杜甫\n白日依山尽,黄河入海流。",
    "赤壁 - 苏轼\n天生我材必有用,千金散尽还复来。",
    "登岳阳楼 - 杜甫\n昔人已乘黄鹤去,此地空余黄鹤楼。"
  ],
  "图片": [
    "https://example.com/去字.jpg",
    "https://example.com/去旅行.png",
    "https://example.com/去工作.gif",
    "https://example.com/去买东西.jpg",
    "https://example.com/去世界.png"
  ],
  "音频": [
    "https://example.com/去字发音.mp3",
    "https://example.com/去的声音.wav"
  ],
  "视频": [
    "https://example.com/去远方.mp4",
    "https://example.com/去追梦.avi"
  ],
  "电影": [
    "《肖申克的救赎》",
    "《阿甘正传》",
    "《星际穿越》",
    "《泰坦尼克号》",
    "《百度星球》"
  ],
  "参考资料": [
    "《说文解字》",
    "《汉语大词典》",
    "《中华字海》",
    "《中国成语大辞典》",
    "《诗词鉴赏大辞典》"
  ],
  "有趣网站": [
    "https://www.zdic.net/",
    "https://www.guoxue.com/",
    "https://www.shicimingju.com/",
    "https://www.wenxuecity.com/",
    "https://www.chinaculture.org/"
  ]
}