{
    "含义": "1. 比较，对照。2. 较量，竞争。3. 相似，类似。4. 比喻。5. 用作介词，表示'比起'。",
    "字形": "左右两个人背靠背站立的样子。",
    "读音": "bǐ",
    "字源": "象形字，像两个人背靠背站立的样子，本义是比较、对照。",
    "常用词组": [
      "比较",
      "比如",
      "比喻",
      "比赛",
      "比例",
      "比重",
      "比方",
      "比拼"
    ],
    "成语": [
      "比比皆是",
      "相形见绌",
      "不比不知道",
      "比上不足比下有余",
      "比翼双飞",
      "相形见绌",
      "不以为然"
    ],
    "例句": [
      "这次考试他比上次进步很多。",
      "与去年相比，今年的收成更好。",
      "这个问题比想象中要复杂得多。",
      "他们正在比赛谁跑得更快。",
      "这个比喻非常恰当，一下子就让人明白了。",
      "这种材料的强度比钢铁还要高。"
    ],
    "短故事": [
      "《比和不比》讲述了两个邻居因为不断比较而失去友谊，最后领悟到每个人都是独特的，不应过分比较的故事。",
      "《比翼鸟》描述了一对相爱的鸟儿，它们一生形影不离，成为了比翼双飞的美好象征。",
      "《比较的智慧》讲述了一个年轻人通过与他人比较，最终认识到自己优缺点，找到人生方向的成长故事。",
      "《无可比拟的爱》描述了一位母亲为孩子付出的爱是无法用任何东西来比较的感人故事。",
      "《比尺》讲述了古代一位木匠制作了一把神奇的尺子，能够测量人心的寓言故事。"
    ],
    "诗词": [
      "李白《静夜思》：\"床前明月光，疑是地上霜。举头望明月，低头思故乡。\"",
      "杜甫《登高》：\"无边落木萧萧下，不尽长江滚滚来。万里悲秋常作客，百年多病独登台。\"",
      "苏轼《水调歌头》：\"明月几时有？把酒问青天。不知天上宫阙，今夕是何年。我欲乘风归去，又恐琼楼玉宇，高处不胜寒。起舞弄清影，何似在人间。\"",
      "辛弃疾《破阵子》：\"醉里挑灯看剑，梦回吹角连营。八百里分麾下炙，五十弦翻塞外声。沙场秋点兵。\"",
      "李清照《如梦令》：\"昨夜雨疏风骤，浓睡不消残酒。试问卷帘人，却道海棠依旧。知否，知否？应是绿肥红瘦。\"",
      "王维《鹿柴》：\"空山不见人，但闻人语响。返景入深林，复照青苔上。\""
    ],
    "图片": [
      "/api/placeholder/400/300",
      "/api/placeholder/400/300",
      "/api/placeholder/400/300",
      "/api/placeholder/400/300",
      "/api/placeholder/400/300"
    ],
    "音频": [
      "比较级和最高级的发音.mp3",
      "比赛开始的哨声.mp3",
      "比喻的语言示例.mp3",
      "比翼鸟的传说朗读.mp3",
      "比较数学题目的讲解.mp3"
    ],
    "视频": [
      "如何正确使用比较级和最高级.mp4",
      "比赛中的精彩时刻集锦.mp4",
      "生动形象的比喻手法教学.mp4",
      "比例尺的使用方法.mp4",
      "比特币与传统货币的对比分析.mp4"
    ],
    "电影": [
      "《比悲伤更悲伤的故事》",
      "《比利·林恩的中场战事》",
      "《比佛利山警探》",
      "《比海更深》",
      "《比得兔》"
    ],
    "参考资料": [
      "《汉语比较范畴研究》",
      "《比较文学与跨文化研究》",
      "《比喻认知语言学探析》",
      "《比较教育学》",
      "《数学中的比与比例》"
    ],
    "有趣网站": [
      "www.metaphoranalogy.com：比喻和类比的在线学习平台",
      "www.comparativemythology.org：比较神话学研究网站",
      "www.competitionpsychology.edu：比赛心理学教育网站",
      "www.analogyquiz.fun：比喻和类比趣味测试网站",
      "www.ratiocalculator.tools：比例计算工具网站"
    ]
  }