{
  "含义": "冬天，寒冷的季节",
  "字形": "上方是冫（两点水），下方是丶（点），整体像冰冻的样子",
  "读音": "dōng",
  "字源": "甲骨文中的冬字像一个人蜷缩在冰天雪地中取暖的样子",
  "常用词组": [
    "冬天",
    "冬季",
    "冬装",
    "冬眠",
    "冬至"
  ],
  "成语": [
    "冬温夏清",
    "冬藏夏长",
    "寒冬腊月",
    "冬扇夏炉",
    "冰天雪地"
  ],
  "例句": [
    "冬天来了，春天还会远吗？",
    "北方的冬天比南方要冷得多。",
    "许多动物会在冬天进入冬眠状态。",
    "冬至这天，我们全家人会一起吃饺子。",
    "冬装的销售旺季通常在十月份开始。"
  ],
  "短故事": [
    "《冬天里的一把火》：在寒冷的冬天，一群流浪汉在街头取暖。一个小女孩走过，给了他们一盒火柴。这小小的温暖，点燃了他们心中的希望之火。",
    "《冬眠的熊》：一只小熊不想冬眠，因为他害怕错过冬天的美景。但他的妈妈告诉他，冬眠是为了在春天醒来时更加强壮。小熊明白了，安心地进入了冬眠。",
    "《冬天的礼物》：一个贫穷的孩子在冬天收到了一双新鞋。他珍惜地穿着，却发现街上有个光脚的老人。孩子毫不犹豫地把鞋送给了老人，感受到了给予的快乐。",
    "《冬至的团圆》：一家人因为工作分散各地，但每年冬至，他们都会不约而同地回到老家，一起包饺子、吃汤圆，感受家的温暖。",
    "《冬日暖阳》：一个独居老人在寒冷的冬天里生病了。邻居们得知后，轮流照顾他，为他送来热汤和温暖。老人感动地说，这比冬日的阳光还要温暖。"
  ],
  "诗词": [
    "《江雪》唐·柳宗元：\"千山鸟飞绝，万径人踪灭。孤舟蓑笠翁，独钓寒江雪。\"",
    "《冬夜读书示子聿》宋·陆游：\"古人学问无遗力，少壮工夫老始成。纸上得来终觉浅，绝知此事要躬行。\"",
    "《冬日》宋·苏轼：\"日脚才过北极弓，萧萧寒气转争兢。梅花落尽荆花发，占得春光第一程。\"",
    "《小雪》宋·陆游：\"天街小雪柳如烟，玉帘垂白不胜寒。唯有楼头望江客，独醒无语理琴弦。\"",
    "《暮冬即事》明·曹学佺：\"野鸟投林鸣角角，村人束柴归叠叠。日脚斜照路上人，山头斜照牛背雪。\""
  ],
  "图片": [
    "/api/placeholder/400/300",
    "/api/placeholder/400/300",
    "/api/placeholder/400/300",
    "/api/placeholder/400/300",
    "/api/placeholder/400/300"
  ],
  "音频": [
    "冬.mp3",
    "冬天来了.mp3",
    "冬眠.mp3",
    "冬至.mp3",
    "冬装.mp3"
  ],
  "视频": [
    "冬天的北京.mp4",
    "冬季养生小贴士.mp4",
    "冬眠动物大揭秘.mp4",
    "冬至习俗介绍.mp4",
    "冬装搭配指南.mp4"
  ],
  "电影": [
    "《冬天的骨头》",
    "《冬荫功》",
    "《冬天不会来》",
    "《冬日恋歌》",
    "《冬眠》"
  ],
  "参考资料": [
    "《说文解字》",
    "《汉字字源字典》",
    "《现代汉语词典》",
    "《中国传统节日文化》",
    "《二十四节气与中国文化》"
  ],
  "有趣网站": [
    "http://www.zdic.net/",
    "http://www.chazidian.com/",
    "http://www.guoxuedashi.com/",
    "http://www.ancientchinesecharacters.com/",
    "http://www.chinesetimeschool.com/"
  ]
}