{
    "含义": "十天干之一；年龄；更改；金属性",
    "字形": "左边是"广"，右边是"庚"",
    "读音": "gēng",
    "字源": "甲骨文象形耕地的形状，后来演变为现在的形态",
    "常用词组": [
      "庚子年",
      "庚申年",
      "庚午年",
      "庚辰年",
      "庚寅年",
      "庚戌年",
      "庚金",
      "庚帖"
    ],
    "成语": [
      "庚癸之呼",
      "庚子赔款",
      "庚午之难",
      "庚申之乱",
      "庚戌变法"
    ],
    "例句": [
      "今年是庚子年，属鼠的本命年。",
      "他的生辰八字中有庚金。",
      "庚午之年，国家发生了重大变革。",
      "庚申年是猴年，很多人都期待着这一年的到来。",
      "她在庚寅年出生，今年刚好60岁。"
    ],
    "短故事": [
      "古代有个名叫贾谊的文学家，他在庚子年写下了著名的《治安策》，建议朝廷要重视民生。皇帝采纳了他的建议，果然在之后的几年里，国家变得更加繁荣。人们因此把庚子年看作是国运昌盛的开始。",
      "宋代著名词人李清照出生于庚辰年。她在《如梦令》中写道："常记溪亭日暮，沉醉不知归路。兴尽晚回舟，误入藕花深处。争渡，争渡，惊起一滩鸥鹭。"这首词被认为是在庚辰年所作，描绘了她对美好生活的向往。",
      "明朝时，有个叫徐霞客的探险家，他在庚午年开始了他著名的游记创作。他说："庚午之年，天地有大运行，正是探索的好时机。"从此，他用了30年时间，走遍了大半个中国，留下了宝贵的地理著作。",
      "清朝康熙皇帝在位期间，遇到了庚戌年。这一年，他下令进行了一系列改革，史称"庚戌变法"。这些改革极大地促进了国家的发展，被后人称为"康乾盛世"的开端。",
      "现代作家巴金在他的小说《家》中写道："那是庚申年的秋天，整个成都城笼罩在一片肃杀的气氛中。"他用庚申年来标记故事的开始，为整个小说设定了一个特殊的时间背景。"
    ],
    "诗词": [
      "《庚子元夕》 苏轼\n东风夜放花千树，更吹落、星如雨。\n宝马雕车香满路。凤箫声动，玉壶光转，一夜鱼龙舞。",
      "《庚午岁三月三日》 白居易\n三月三日天气新，长安水边多丽人。\n态浓意远淑且真，肌理细腻骨肉匀。\n",
      "《庚戌之秋》 陆游\n塞上长城空自许，镜中衰鬓已先秋。\n人生自是有情痴，此恨不关风与月。\n",
      "《庚申年春》 杜甫\n二月已破三月来，渭水暗随红叶去。\n今春有味最寻常，一夜绿荷惊白鹭。",
      "《庚子元日》 王安石\n爆竹声中一岁除，春风送暖入屠苏。\n千门万户曈曈日，总把新桃换旧符。"
    ],
    "图片": [
      "/api/placeholder/400/300",
      "/api/placeholder/400/300",
      "/api/placeholder/400/300",
      "/api/placeholder/400/300",
      "/api/placeholder/400/300"
    ],
    "音频": [
      "庚子年新年祝福.mp3",
      "庚金命理解析.mp3",
      "庚申年民俗介绍.mp3",
      "庚午年历史事件回顾.mp3",
      "庚辰年龙年歌.mp3"
    ],
    "视频": [
      "十天干之庚的由来与意义.mp4",
      "庚子年鼠年文化节目.mp4",
      "庚金在中医养生中的应用.mp4",
      "庚申年猴年习俗介绍.mp4",
      "庚午年马年庆典活动.mp4"
    ],
    "电影": [
      "《庚子年》",
      "《庚申劫》",
      "《庚午风云》",
      "《庚辰传奇》",
      "《庚金岁月》"
    ],
    "参考资料": [
      "《说文解字》 许慎",
      "《字源》 谷衍奎",
      "《汉语大字典》 汉语大字典编辑委员会",
      "《中国文化符号词典》 舒新城",
      "《干支纪年法与中国文化》 陈久金"
    ],
    "有趣网站": [
      "汉典 (https://www.zdic.net/)",
      "象形字典 (https://www.vividict.com/)",
      "汉语多功能字库 (https://hanziyuan.net/)",
      "Chinese Etymology (https://hanziyuan.net/)",
      "汉字全息资源应用系统 (http://qxk.bnu.edu.cn/)"
    ]
  }